{
	"subtitle": "Game Setting",
	"background": {
		"image": "gui.background",
		"scale": [
			0,
			0,
			1920,
			1022
		]
	},
	"widgets": {
		"scroll_bar": {
			"type": "scroll_bar",
			"pos": [
				"win_width / 2 - 100.0 * scale",
				"win_height / 2 - 30.0 * scale"
			]
			,
			"size": [
				"200.0 * scale",
				"20.0 * scale"
			]
			,
			"default_value": 0.30,
			"background_color": [
				12,
				12,
				12,
				255
			],
			"scrollbar_color": [
				65,
				65,
				65,
				255
			],
			"outline": {
				"color": [
					114,
					145,
					233,
					255
				]
				,
				"width": 2
			}
		},
		"textbox": {
			"type": "textbox",
			"pos": [
				"win_width / 2 - 100.0 * scale",
				"win_height / 2 + 30.0 * scale"
			]
		,
			"size": [
				"200.0 * scale",
				"20.0 * scale"
			]
		,
			"default_value": 0.30,
			"background_color": [
				12,
				12,
				12,
				255
			],
			"text_color": [
				255,
				255,
				255,
				255
			],
			"text_size": "15.0 * scale",
			"hint": "Hint!",
			"outline": {
				"color": [
					114,
					145,
					233,
					255
				],
				"width": 2
			}
		}
	}
}
